hivemind_presence/__init__.py
hivemind_presence/devices.py
hivemind_presence/discovery.py
hivemind_presence/presence.py
hivemind_presence/ssdp.py
hivemind_presence/upnp_server.py
hivemind_presence/utils.py
hivemind_presence/version.py
hivemind_presence/zero.py
HiveMind_presence-0.0.2a4.dist-info/LICENSE
HiveMind_presence-0.0.2a4.dist-info/METADATA
HiveMind_presence-0.0.2a4.dist-info/WHEEL
HiveMind_presence-0.0.2a4.dist-info/top_level.txt
HiveMind_presence-0.0.2a4.dist-info/RECORD
